djdantic/__init__.py
djdantic/exceptions.py
djdantic/fields.py
djdantic/models.py
djdantic/context/__init__.py
djdantic/context/access.py
djdantic/schemas/__init__.py
djdantic/schemas/access.py
djdantic/schemas/error.py
djdantic/schemas/price.py
djdantic/utils/__init__.py
djdantic/utils/dict.py
djdantic/utils/pydantic.py
djdantic/utils/typing.py
djdantic/utils/pydantic_django/__init__.py
djdantic/utils/pydantic_django/checks.py
djdantic/utils/pydantic_django/django_to_pydantic.py
djdantic/utils/pydantic_django/pydantic.py
djdantic/utils/pydantic_django/pydantic_to_django.py
djdantic/utils/pydantic_django/utils.py
djdantic-0.0.25.dist-info/LICENSE
djdantic-0.0.25.dist-info/METADATA
djdantic-0.0.25.dist-info/WHEEL
djdantic-0.0.25.dist-info/top_level.txt
djdantic-0.0.25.dist-info/RECORD
