Metadata-Version: 2.1
Name: djdantic
Version: 0.0.25
Summary: Utilities to use pydantic with the django orm
Home-page: https://github.com/Voltane-EU/djdantic
Author: Manuel Stingl
Author-email: opensource@voltane.eu
License: GNU LGPLv2.1
Classifier: Programming Language :: Python :: 3
Classifier: License :: OSI Approved :: GNU Lesser General Public License v2 or later (LGPLv2+)
Classifier: Operating System :: OS Independent
Classifier: Framework :: Django
Classifier: Framework :: FastAPI
Classifier: Topic :: Utilities
Requires-Python: >=3.6
License-File: LICENSE
Requires-Dist: django >=3.0
Requires-Dist: pydantic >=1.8
Requires-Dist: python-jose[cryptography]
Requires-Dist: sentry-tools >=0.0.2
Requires-Dist: async-sync-tools >=0.0.3
